dicom2jpg/__init__.py
dicom2jpg/__version__.py
dicom2jpg/utils.py
dicom2jpg-0.1.10.dist-info/.DS_Store
dicom2jpg-0.1.10.dist-info/LICENSE
dicom2jpg-0.1.10.dist-info/METADATA
dicom2jpg-0.1.10.dist-info/WHEEL
dicom2jpg-0.1.10.dist-info/top_level.txt
dicom2jpg-0.1.10.dist-info/RECORD
